package/__init__.py
package/__main__.py
package/clients/__init__.py
package/clients/discord.py
package/clients/telegram.py
package/emojis/__init__.py
package/logger/__init__.py
multi_logger_py-0.1.0.dist-info/METADATA
multi_logger_py-0.1.0.dist-info/WHEEL
multi_logger_py-0.1.0.dist-info/licenses/LICENSE
multi_logger_py-0.1.0.dist-info/RECORD
